{
  "main": {
    "id": "bfc20f3929d8ab0a",
    "type": "split",
    "children": [
      {
        "id": "30f32dde218d00c5",
        "type": "tabs",
        "children": [
          {
            "id": "0469ad66406abaa3",
            "type": "leaf",
            "state": {
              "type": "markdown",
              "state": {
                "file": "COMP411/PatchEmbedding.md",
                "mode": "source",
                "source": false
              },
              "icon": "lucide-file",
              "title": "PatchEmbedding"
            }
          }
        ]
      }
    ],
    "direction": "vertical"
  },
  "left": {
    "id": "b2f50821f1e1ebec",
    "type": "split",
    "children": [
      {
        "id": "e4f5f17ad57b1877",
        "type": "tabs",
        "children": [
          {
            "id": "a36e7ec4ede93a26",
            "type": "leaf",
            "state": {
              "type": "file-explorer",
              "state": {
                "sortOrder": "alphabetical"
              },
              "icon": "lucide-folder-closed",
              "title": "Files"
            }
          },
          {
            "id": "50ecdb321868b631",
            "type": "leaf",
            "state": {
              "type": "search",
              "state": {
                "query": "",
                "matchingCase": false,
                "explainSearch": false,
                "collapseAll": false,
                "extraContext": false,
                "sortOrder": "alphabetical"
              },
              "icon": "lucide-search",
              "title": "Search"
            }
          },
          {
            "id": "42ecd33fc5069d19",
            "type": "leaf",
            "state": {
              "type": "bookmarks",
              "state": {},
              "icon": "lucide-bookmark",
              "title": "Bookmarks"
            }
          }
        ]
      }
    ],
    "direction": "horizontal",
    "width": 311.5
  },
  "right": {
    "id": "9925cb7a7adfa481",
    "type": "split",
    "children": [
      {
        "id": "dfc53f8d59f757d4",
        "type": "tabs",
        "children": [
          {
            "id": "9155fca2f0b09d84",
            "type": "leaf",
            "state": {
              "type": "backlink",
              "state": {
                "file": "COMP411/slides/Lec01-ML-Basics.pdf",
                "collapseAll": false,
                "extraContext": false,
                "sortOrder": "alphabetical",
                "showSearch": false,
                "searchQuery": "",
                "backlinkCollapsed": false,
                "unlinkedCollapsed": true
              },
              "icon": "links-coming-in",
              "title": "Backlinks for Lec01-ML-Basics"
            }
          },
          {
            "id": "2f261258a9a32c42",
            "type": "leaf",
            "state": {
              "type": "outgoing-link",
              "state": {
                "file": "COMP411/slides/Lec01-ML-Basics.pdf",
                "linksCollapsed": false,
                "unlinkedCollapsed": true
              },
              "icon": "links-going-out",
              "title": "Outgoing links from Lec01-ML-Basics"
            }
          },
          {
            "id": "ed91decc29604eb7",
            "type": "leaf",
            "state": {
              "type": "tag",
              "state": {
                "sortOrder": "frequency",
                "useHierarchy": true
              },
              "icon": "lucide-tags",
              "title": "Tags"
            }
          },
          {
            "id": "fec7dc154eba9047",
            "type": "leaf",
            "state": {
              "type": "outline",
              "state": {
                "file": "COMP411/slides/Lec01-ML-Basics.pdf"
              },
              "icon": "lucide-list",
              "title": "Outline of Lec01-ML-Basics"
            }
          }
        ]
      }
    ],
    "direction": "horizontal",
    "width": 300,
    "collapsed": true
  },
  "left-ribbon": {
    "hiddenItems": {
      "switcher:Open quick switcher": false,
      "graph:Open graph view": false,
      "canvas:Create new canvas": false,
      "daily-notes:Open today's daily note": false,
      "templates:Insert template": false,
      "command-palette:Open command palette": false
    }
  },
  "active": "0469ad66406abaa3",
  "lastOpenFiles": [
    "COMP411/PatchEmbedding.md",
    "COMP411/Max Pooling.md",
    "COMP411/Convolutional Layer.md",
    "COMP411/Convo.md",
    "COMP411/Image Interpolation.md",
    "COMP411/Untitled.md",
    "images/Screenshot From 2025-01-08 17-26-16.png",
    "images/Pasted image 20250108172530.png",
    "COMP411/LSTM.md",
    "COMP411/exercises/HW4_murat.ipynb",
    "images/Pasted image 20250108181607.png",
    "images/Pasted image 20250108181440.png",
    "images/Pasted image 20250108181252.png",
    "images/Pasted image 20250108181215.png",
    "images/Pasted image 20250108180140.png",
    "images/Pasted image 20250108172838.png",
    "images/Screenshot From 2025-01-08 17-26-16 1.png",
    "COMP411/RNN.md",
    "MATH103/Lectures.pdf",
    "MATH103/MATH103 - Abstract Mathematics.md",
    "COMP341/slides/9 - Bayesian Networks_Representation.pdf",
    "COMP341/slides/10 - Bayesian Networks_Exact Inference.pdf",
    "COMP341/slides/L - Bayesian Networks.md",
    "Untitled.md",
    "images/Pasted image 20241226135259.png",
    "COMP341/L8 - Probability.md",
    "COMP341/slides/3 - Uninformed Search.pdf",
    "COMP341/slides/8 - Probability.pdf",
    "COMP341/L7 - Games - Minimax.md",
    "COMP341/L5 & 6- Local Search + CSP.md",
    "COMP341/slides/7 - Adversarial Search.pdf",
    "COMP341/slides/6 - CSPs.pdf",
    "COMP341/slides/5 - LocalSearch.pdf",
    "COMP341/slides/14 - Machine Learning.pdf",
    "Tracker.canvas",
    "COMP341/L3&4 - Search Algorithms.md",
    "COMP341/L2 - Agents.md",
    "COMP341/L1 - Introduction.md",
    "COMP341/Obsidian Notes (unordered)/Least Constraining Value.md",
    "COMP341/Obsidian Notes (unordered)/A-star Search.md",
    "COMP341/Obsidian Notes (unordered)/Uniform Cost Search.md",
    "COMP411/COMP411 - Computer Vision With AI.md",
    "COMP341/Obsidian Notes (unordered)/COMP341 - Introduction To AI.md",
    "COMP350/Lecture 7 - Dockerfile.md",
    "COMP350/COMP350 - DevOps.md",
    "COMP350/conp350 mt1 answers.md",
    "index.md"
  ]
}